libsql_client/__init__.py
libsql_client/client.py
libsql_client/config.py
libsql_client/create_client.py
libsql_client/hrana/__init__.py
libsql_client/hrana/client.py
libsql_client/hrana/conn.py
libsql_client/hrana/convert.py
libsql_client/hrana/id_alloc.py
libsql_client/hrana/proto.py
libsql_client/http.py
libsql_client/result.py
libsql_client/sqlite3.py
libsql_client/sync.py
libsql_client-0.2.2.dist-info/LICENSE.md
libsql_client-0.2.2.dist-info/WHEEL
libsql_client-0.2.2.dist-info/METADATA
libsql_client-0.2.2.dist-info/RECORD
