Metadata-Version: 2.1
Name: libsql-client
Version: 0.2.2
Summary: Python SDK for libSQL
Home-page: https://github.com/libsql/libsql-client-py
License: MIT
Author: Jan Špaček
Author-email: honza@chiselstrike.com
Requires-Python: >=3.7,<4.0
Classifier: License :: OSI Approved :: MIT License
Classifier: Operating System :: OS Independent
Classifier: Programming Language :: Python :: 3
Classifier: Programming Language :: Python :: 3.7
Classifier: Programming Language :: Python :: 3.8
Classifier: Programming Language :: Python :: 3.9
Classifier: Programming Language :: Python :: 3.10
Requires-Dist: aiohttp (>=3.0,<4.0)
Requires-Dist: typing-extensions (>=4.5,<5.0)
Project-URL: Documentation, https://libsql.org/libsql-client-py/
Project-URL: Repository, https://github.com/libsql/libsql-client-py
